__init__.py
pandas_orm/__init__.py
pandas_orm/base/__init__.py
pandas_orm/base/dataframe.py
pandas_orm/base/describe.py
pandas_orm/base/exceptions.py
pandas_orm/base/log.py
pandas_orm/django/__init__.py
pandas_orm/django/dataframe.py
pandas_orm/django/db.py
pandas_orm/django/model.py
pandas_orm/django/query.py
pandas_orm/django/setup.py
pandas_orm/django/crud/__init__.py
pandas_orm/django/crud/naive_save_arguments.py
pandas_orm/django/crud/save.py
pandas_orm/django/describe/__init__.py
pandas_orm/django/describe/model_describe.py
pandas_orm/django/mixins/__init__.py
pandas_orm/django/mixins/base_model_fields_mixin.py
pandas_orm/django/mixins/dataframe_mixin.py
pandas_orm/sqlalchemy/__init__.py
pandas_orm/sqlalchemy/dataframe.py
pandas_orm/sqlalchemy/exceptions.py
pandas_orm/sqlalchemy/execute_sql.py
pandas_orm/sqlalchemy/model_manager.py
pandas_orm/sqlalchemy/query.py
pandas_orm/sqlalchemy/crud/__init__.py
pandas_orm/sqlalchemy/crud/naive_save_arguments.py
pandas_orm/sqlalchemy/crud/save.py
pandas_orm/sqlalchemy/describe/__init__.py
pandas_orm/sqlalchemy/describe/model_describe.py
pandas_orm/sqlalchemy/session/__init__.py
pandas_orm/sqlalchemy/session/sqlalchemy_db.py
pandas_orm-0.0.16.dist-info/LICENSE
pandas_orm-0.0.16.dist-info/METADATA
pandas_orm-0.0.16.dist-info/WHEEL
pandas_orm-0.0.16.dist-info/top_level.txt
pandas_orm-0.0.16.dist-info/RECORD
