Metadata-Version: 2.1
Name: pandas-orm
Version: 0.0.16
Summary: pandas orm with django and sqlalchemy framework with bulk C.R.U.D operations
Author-email: Ilya Shusterman <shusterilyaman@gmail.com>
License: Copyright (c) 2022 The Python Packaging Authority        
Project-URL: Homepage, https://github.com/ilyashusterman/pandas-orm
Project-URL: Bug Tracker, https://github.com/ilyashusterman/pandas-orm/issues
Keywords: pandas,orm,django,sqlalchemy,dataframe
Classifier: Programming Language :: Python :: 3
Classifier: License :: OSI Approved :: MIT License
Classifier: Operating System :: OS Independent
Requires-Python: >=3.8.9
License-File: LICENSE
Requires-Dist: pandas (>=1.4.4)
Requires-Dist: SQLAlchemy (>=1.4.41)
Requires-Dist: Django (>=4.1.1)
